cobrapy_bigg_client/__init__.py
cobrapy_bigg_client/_version.py
cobrapy_bigg_client/client.py
cobrapy_bigg_client/tests/__init__.py
cobrapy_bigg_client/tests/conftest.py
cobrapy_bigg_client/tests/test_client.py
cobrapy_bigg_client/tests/fixtures/__init__.py
cobrapy_bigg_client/tests/fixtures/models/__init__.py
cobrapy_bigg_client-1.0.11.dist-info/METADATA
cobrapy_bigg_client-1.0.11.dist-info/RECORD
cobrapy_bigg_client-1.0.11.dist-info/WHEEL
cobrapy_bigg_client-1.0.11.dist-info/top_level.txt
